zyb_charts/__init__.py
zyb_charts/charts.py
zyb_charts/js/echarts.min.js
zyb_charts/templates/components.html
zyb_charts/templates/macro
zyb_charts/templates/simple_chart.html
zyb_charts/templates/simple_globe.html
zyb_charts/templates/simple_page.html
zyb_charts/templates/simple_tab.html
zyb_charts-0.12.dist-info/LICENSE
zyb_charts-0.12.dist-info/METADATA
zyb_charts-0.12.dist-info/WHEEL
zyb_charts-0.12.dist-info/top_level.txt
zyb_charts-0.12.dist-info/RECORD
